odoo10_addon_l10n_fr_siret-10.0.1.0.0.99.dev8-py2.7-nspkg.pth
odoo/addons/l10n_fr_siret/README.rst
odoo/addons/l10n_fr_siret/__init__.py
odoo/addons/l10n_fr_siret/__manifest__.py
odoo/addons/l10n_fr_siret/demo/partner_demo.xml
odoo/addons/l10n_fr_siret/i18n/bg.po
odoo/addons/l10n_fr_siret/i18n/da.po
odoo/addons/l10n_fr_siret/i18n/de.po
odoo/addons/l10n_fr_siret/i18n/el_GR.po
odoo/addons/l10n_fr_siret/i18n/es.po
odoo/addons/l10n_fr_siret/i18n/es_MX.po
odoo/addons/l10n_fr_siret/i18n/fi.po
odoo/addons/l10n_fr_siret/i18n/fr.po
odoo/addons/l10n_fr_siret/i18n/fr_CH.po
odoo/addons/l10n_fr_siret/i18n/hr.po
odoo/addons/l10n_fr_siret/i18n/it.po
odoo/addons/l10n_fr_siret/i18n/l10n_fr_siret.pot
odoo/addons/l10n_fr_siret/i18n/nb_NO.po
odoo/addons/l10n_fr_siret/i18n/nl.po
odoo/addons/l10n_fr_siret/i18n/pt.po
odoo/addons/l10n_fr_siret/i18n/pt_BR.po
odoo/addons/l10n_fr_siret/i18n/sl.po
odoo/addons/l10n_fr_siret/models/__init__.py
odoo/addons/l10n_fr_siret/models/company.py
odoo/addons/l10n_fr_siret/models/partner.py
odoo/addons/l10n_fr_siret/static/description/icon.png
odoo/addons/l10n_fr_siret/views/company.xml
odoo/addons/l10n_fr_siret/views/partner.xml
odoo10_addon_l10n_fr_siret-10.0.1.0.0.99.dev8.dist-info/METADATA
odoo10_addon_l10n_fr_siret-10.0.1.0.0.99.dev8.dist-info/RECORD
odoo10_addon_l10n_fr_siret-10.0.1.0.0.99.dev8.dist-info/WHEEL
odoo10_addon_l10n_fr_siret-10.0.1.0.0.99.dev8.dist-info/namespace_packages.txt
odoo10_addon_l10n_fr_siret-10.0.1.0.0.99.dev8.dist-info/top_level.txt
